README.md
setup.py
saturn/__init__.py
saturn/scope.py
saturn/terminal.py
saturn/version.py
saturn_python.egg-info/PKG-INFO
saturn_python.egg-info/SOURCES.txt
saturn_python.egg-info/dependency_links.txt
saturn_python.egg-info/entry_points.txt
saturn_python.egg-info/not-zip-safe
saturn_python.egg-info/top_level.txt