Metadata-Version: 2.1
Name: saturn-python
Version: 1.3
Summary: Saturn allows to rerun python scripts skipping some places that were defined in previous runs.
Home-page: https://github.com/fomalhaut88/saturn
Author: Alexander Khlebushchev
License: MIT
Platform: UNKNOWN
